openvino_workbench/__init__.py
openvino_workbench/arguments_parser.py
openvino_workbench/constants.py
openvino_workbench/container.py
openvino_workbench/docker_config_creator.py
openvino_workbench/image.py
openvino_workbench/main.py
openvino_workbench/utils.py
openvino_workbench-2022.3.0.dist-info/LICENSE
openvino_workbench-2022.3.0.dist-info/METADATA
openvino_workbench-2022.3.0.dist-info/WHEEL
openvino_workbench-2022.3.0.dist-info/entry_points.txt
openvino_workbench-2022.3.0.dist-info/top_level.txt
openvino_workbench-2022.3.0.dist-info/RECORD
