Metadata-Version: 2.1
Name: openvino-workbench
Version: 2022.3.0
Summary: DL Workbench is the official UI environment of the OpenVINO™ toolkit.
Home-page: https://github.com/openvinotoolkit/workbench_aux
Author: Intel® Corporation
Author-email: openvino_pushbot@intel.com
License: OSI Approved :: Apache Software License
Project-URL: Documentation, https://docs.openvino.ai/latest/workbench_docs_Workbench_DG_Introduction.html
Project-URL: Feedback, https://community.intel.com/t5/Intel-Distribution-of-OpenVINO/bd-p/distribution-openvino-toolkit
Project-URL: Troubleshooting, https://community.intel.com/t5/Intel-Distribution-of-OpenVINO/bd-p/distribution-openvino-toolkit
Classifier: Programming Language :: Python :: 3
Classifier: License :: OSI Approved :: Apache Software License
Classifier: Operating System :: OS Independent
License-File: LICENSE
Requires-Dist: docker (==4.4.4)
Requires-Dist: tqdm (==4.60.0)
Requires-Dist: requests (==2.22.0)
Requires-Dist: psutil (==5.8.0)
